pydantic_faker/__init__.py
pydantic_faker/cli.py
pydantic_faker/core.py
pydantic_faker/server.py
pydantic_faker-0.4.0.dist-info/METADATA
pydantic_faker-0.4.0.dist-info/WHEEL
pydantic_faker-0.4.0.dist-info/entry_points.txt
pydantic_faker-0.4.0.dist-info/licenses/LICENSE
pydantic_faker-0.4.0.dist-info/RECORD
