Metadata-Version: 2.4
Name: pydantic-faker
Version: 0.4.0
Summary: A CLI tool to generate fake data from Pydantic models.
Project-URL: Homepage, https://github.com/vvandriichuk/pydantic-faker
Project-URL: Repository, https://github.com/vvandriichuk/pydantic-faker
Project-URL: Issues, https://github.com/vvandriichuk/pydantic-faker/issues
Author-email: Viktor Andriichuk <v.andriichuk@gmail.com>
License: MIT
License-File: LICENSE
Classifier: Development Status :: 3 - Alpha
Classifier: Intended Audience :: Developers
Classifier: License :: OSI Approved :: MIT License
Classifier: Programming Language :: Python :: 3
Classifier: Programming Language :: Python :: 3.12
Classifier: Topic :: Software Development :: Testing :: Mocking
Classifier: Topic :: Utilities
Classifier: Typing :: Typed
Requires-Python: >=3.12
Requires-Dist: faker<38.0.0,>=37.0.0
Requires-Dist: fastapi<0.112.0,>=0.90.0
Requires-Dist: pydantic<4.0.0,>=2.0.0
Requires-Dist: pydantic[email]<4.0.0,>=2.0.0
Requires-Dist: rich<15.0.0,>=13.0.0
Requires-Dist: typer<2.0.0,>=0.9.0
Requires-Dist: uvicorn[standard]<0.30.0,>=0.20.0
Provides-Extra: dev
Requires-Dist: mypy>=1.15.0; extra == 'dev'
Requires-Dist: pre-commit>=4.1.0; extra == 'dev'
Requires-Dist: pyright>=1.1.401; extra == 'dev'
Requires-Dist: pytest>=8.3.5; extra == 'dev'
Requires-Dist: ruff>=0.11.0; extra == 'dev'
Requires-Dist: types-requests; extra == 'dev'
